openapi/automotive/openapi.yaml
openapi/identity/openapi.yaml
openapi/maintenance/openapi.yaml
openapi/services/openapi.yaml
lojack_clients/automotive/__init__.py
lojack_clients/automotive/api/__init__.py
lojack_clients/automotive/api/default/__init__.py
lojack_clients/automotive/api/default/get_automotive_dealer_profile.py
lojack_clients/automotive/client.py
lojack_clients/automotive/models/__init__.py
lojack_clients/automotive/models/get_automotive_dealer_profile_response_200.py
lojack_clients/automotive/models/get_automotive_dealer_profile_response_200_dealership_address.py
lojack_clients/automotive/models/get_automotive_dealer_profile_response_200_vehicle_valuation.py
lojack_clients/automotive/types.py
lojack_clients/identity/__init__.py
lojack_clients/identity/api/__init__.py
lojack_clients/identity/api/default/__init__.py
lojack_clients/identity/api/default/get_identity_token.py
lojack_clients/identity/client.py
lojack_clients/identity/models/__init__.py
lojack_clients/identity/models/get_identity_token_response_200.py
lojack_clients/identity/types.py
lojack_clients/maintenance/__init__.py
lojack_clients/maintenance/api/__init__.py
lojack_clients/maintenance/api/default/__init__.py
lojack_clients/maintenance/api/default/get_maintenance_schedule.py
lojack_clients/maintenance/api/default/get_repair_orders.py
lojack_clients/maintenance/client.py
lojack_clients/maintenance/models/__init__.py
lojack_clients/maintenance/models/get_maintenance_schedule_response_200.py
lojack_clients/maintenance/models/get_maintenance_schedule_response_200_content_item.py
lojack_clients/maintenance/models/get_maintenance_schedule_response_200_content_item_service_schedule_item.py
lojack_clients/maintenance/models/get_maintenance_schedule_response_200_content_item_service_schedule_item_service_items.py
lojack_clients/maintenance/models/get_maintenance_schedule_response_200_content_item_service_schedule_item_service_items_severity.py
lojack_clients-1.0.2.dist-info/LICENSE
lojack_clients-1.0.2.dist-info/WHEEL
lojack_clients-1.0.2.dist-info/METADATA
lojack_clients-1.0.2.dist-info/RECORD
