Metadata-Version: 2.1
Name: lojack-clients
Version: 1.0.2
Summary: A collection of unofficial client libraries for accessing Spireon's LoJack APIs
Home-page: https://github.com/scorgn/lojack-clients
Keywords: lojack,spireon,sdk
Author: Shawn Corrigan
Author-email: sha.wnja.mesc@gmail.com
Requires-Python: >=3.7,<4.0
Classifier: License :: OSI Approved :: MIT License
Classifier: Programming Language :: Python
Classifier: Programming Language :: Python :: 3
Classifier: Programming Language :: Python :: 3.10
Classifier: Programming Language :: Python :: 3.7
Classifier: Programming Language :: Python :: 3.8
Classifier: Programming Language :: Python :: 3.9
Classifier: Topic :: Software Development :: Libraries
Requires-Dist: attrs (>=21.3.0)
Requires-Dist: httpx (>=0.15.4,<0.23.0)
Requires-Dist: python-dateutil (>=2.8.0,<3.0.0)
Requires-Dist: uuid
Project-URL: Repository, https://github.com/scorgn/lojack-clients
